{
  "id": "cb_001_hi",
  "category": "classroom_behaviour",
  "grade_band": "Preparatory (3-5)",
  "subject": "general",
  "language": "hi",
  "title": "बच्चे lesson के दौरान ध्यान नहीं देते",
  "query_text": "बच्चे lesson के दौरान ध्यान नहीं देते",
  "response": {
    "session_id": "cc0b614b-78f7-498c-bb0d-4e85deda6f2e",
    "language": "hi",
    "immediate_steps": {
      "title": "तत्काल सलाह",
      "steps": [
        "पाठ की शुरुआत एक छोटे से सवाल या पहेली से करें — जैसे 'क्या तुमने कभी चींटी को हाथी से लड़ते देखा है?' इससे बच्चों की जिज्ञासा जागती है।",
        "हर 5-7 मिनट पर गतिविधि बदलें — सुनना, बोलना, करना। एक ही तरीके से पढ़ाने पर ध्यान भटकता है।",
        "जो बच्चा ध्यान न दे, उसे डाँटने की बजाय उससे एक आसान सवाल पूछें — इससे वह पाठ से जुड़ जाता है।"
      ]
    },
    "classroom_activity": {
      "title": "कक्षा गतिविधि — 'बोलो और दोहराओ'",
      "activity": "NCERT कक्षा 4 की कहानी 'मदन' की तरह — कोई भी पाठ पढ़ाते समय एक मज़ेदार आवाज़ या लय वाली पंक्ति चुनें। पूरी कक्षा को उसे एक साथ ज़ोर से दोहराने को कहें। फिर लड़के अलग, लड़कियाँ अलग दोहराएँ। इससे सभी बच्चे सक्रिय रहते हैं और ध्यान बना रहता है।",
      "materials": "केवल पाठ्यपुस्तक — कुछ और नहीं चाहिए",
      "time_required": "10 मिनट"
    },
    "inclusion_strategy": {
      "title": "समावेश रणनीति",
      "strategy": "जो बच्चे सबसे कम ध्यान देते हैं, उन्हें 'सहायक' की भूमिका दें — जैसे 'तुम बताओ अगला वाक्य कौन पढ़ेगा।' TaRL पद्धति के अनुसार, बच्चे को ज़िम्मेदारी मिलने पर वह अपने आप जुड़ता है।"
    },
    "reflection_prompt": {
      "title": "चिंतन",
      "question": "आज की कक्षा में कौन से 2 मिनट थे जब सबसे ज़्यादा बच्चे ध्यान दे रहे थे — उस पल में आप क्या कर रहे थे?"
    },
    "source_citation": {
      "title": "संदर्भ",
      "reference": "TaRL (Teaching at the Right Level) — Pratham methodology; NCERT Class-4 Hindi 'वीणा' — सक्रिय भागीदारी आधारित शिक्षण; NEP 2020, Section 5.4 — Activity-based and experiential learning"
    },
    "response_time_ms": 18995,
    "from_cache": false
  }
}